{
    "activities": [

    ],
    "certificates": [
        {
            "img": "https://raw.githubusercontent.com/imjustnon/portfolio_assets/main/assets/images/certificates/pjbl1.jpg",
            "url": "assets/images/activity/Picture2-crop.jpg",
            "title": [
                "ชนะการประกวดโปรเจค PjBL ระดับ ปวช. 1"
            ],
            "description": [
                "ชั้น : ปวช.1"
            ]
        }
    ],
    "projects": [

    ],
    "personal": {
        "myself": [],
        "mom": [],
        "dad": [],
        "schools": [
            {
                "img": "assets/images/portfolio/ssm.jpg",
                "url": "https://www.ssm.ac.th/",
                "title": [
                    "จบการศึกษาระดับ มัธยมศึกษาปีที่3",
                    "โรงเรียนเซนต์เเมรี่ (สมุทรปราการ)"
                ],
                "description": [],
                "button": {
                    "facebook": "https://web.facebook.com/SaintmarySM/",
                    "website": "https://www.ssm.ac.th/"
                },
                "aosAnimation": "fade-right"
            },
            {
                "img": "assets/images/portfolio/sbtvc.jpg",
                "url": "http://sbtvc.ac.th/gcms/index.php",
                "title": [
                    "กำลังศึกษาระดับ ปวช.",
                    "วิทยาลัยอาชีวศึกษาเทคโนโลยีฐานวิทยาศาสตร์ (ชลบุรี)"
                ],
                "description": [],
                "button": {
                    "facebook": "https://web.facebook.com/sbtvc/",
                    "website": "http://sbtvc.ac.th/gcms/index.php"
                },
                "aosAnimation": "fade-left"
            }
        ]
    }
}